typeguess/__init__.py
typeguess/guess_core.py
typeguess-0.0.2.dist-info/DESCRIPTION.rst
typeguess-0.0.2.dist-info/METADATA
typeguess-0.0.2.dist-info/RECORD
typeguess-0.0.2.dist-info/WHEEL
typeguess-0.0.2.dist-info/metadata.json
typeguess-0.0.2.dist-info/top_level.txt
